paperdl/__init__.py
paperdl/paperdl.py
paperdl/modules/__init__.py
paperdl/modules/sources/__init__.py
paperdl/modules/sources/arxiv.py
paperdl/modules/sources/baiduwenku.py
paperdl/modules/sources/base.py
paperdl/modules/sources/googlescholar.py
paperdl/modules/sources/scihub.py
paperdl/modules/utils/__init__.py
paperdl/modules/utils/downloader.py
paperdl/modules/utils/logger.py
paperdl/modules/utils/misc.py
paperdl-0.1.6.dist-info/LICENSE
paperdl-0.1.6.dist-info/METADATA
paperdl-0.1.6.dist-info/WHEEL
paperdl-0.1.6.dist-info/entry_points.txt
paperdl-0.1.6.dist-info/top_level.txt
paperdl-0.1.6.dist-info/zip-safe
paperdl-0.1.6.dist-info/RECORD
