Metadata-Version: 2.1
Name: paperdl
Version: 0.1.6
Summary: Paperdl: Search and download paper from specific websites
Home-page: https://github.com/CharlesPikachu/paperdl
Author: Charles
Author-email: charlesblwx@gmail.com
License: Apache License 2.0
Platform: UNKNOWN
Classifier: License :: OSI Approved :: Apache Software License
Classifier: Programming Language :: Python :: 3
Classifier: Intended Audience :: Developers
Classifier: Operating System :: OS Independent
License-File: LICENSE
Requires-Dist: requests
Requires-Dist: beautifulsoup4
Requires-Dist: lxml
Requires-Dist: click
Requires-Dist: prettytable
Requires-Dist: alive-progress
